gm_termcontrol/__init__.py
gm_termcontrol/termcontrol.py
gm_termcontrol-0.0.3.dist-info/LICENSE
gm_termcontrol-0.0.3.dist-info/METADATA
gm_termcontrol-0.0.3.dist-info/WHEEL
gm_termcontrol-0.0.3.dist-info/top_level.txt
gm_termcontrol-0.0.3.dist-info/RECORD
